CHANGES.txt
LICENCE.txt
MANIFEST.in
README.md
VERSION.txt
requirements.txt
setup.py
./CHANGES.txt
./LICENCE.txt
./README.md
./VERSION.txt
./requirements.txt
./build/lib/jobmanager/VERSION.txt
./jobmanager/CLIENT.VERSION.txt
./jobmanager_client.egg-info/SOURCES.txt
./jobmanager_client.egg-info/dependency_links.txt
./jobmanager_client.egg-info/requires.txt
./jobmanager_client.egg-info/top_level.txt
./venv/lib/python3.7/site-packages/pip-10.0.1.dist-info/LICENSE.txt
./venv/lib/python3.7/site-packages/pip-10.0.1.dist-info/entry_points.txt
./venv/lib/python3.7/site-packages/pip-10.0.1.dist-info/top_level.txt
./venv/lib/python3.7/site-packages/setuptools-39.0.1.dist-info/LICENSE.txt
./venv/lib/python3.7/site-packages/setuptools-39.0.1.dist-info/dependency_links.txt
./venv/lib/python3.7/site-packages/setuptools-39.0.1.dist-info/entry_points.txt
./venv/lib/python3.7/site-packages/setuptools-39.0.1.dist-info/top_level.txt
bin/jobmanager-client
jobmanager/CLIENT.VERSION.txt
jobmanager/__init__.py
jobmanager/client.py
jobmanager_client.egg-info/PKG-INFO
jobmanager_client.egg-info/SOURCES.txt
jobmanager_client.egg-info/dependency_links.txt
jobmanager_client.egg-info/requires.txt
jobmanager_client.egg-info/top_level.txt