Metadata-Version: 1.1
Name: jobmanager-client
Version: 0.14.3
Summary: Job Manager Client
Home-page: https://github.com/ronhanson/python-jobmanager-client
Author: Ronan Delacroix
Author-email: ronan.delacroix@gmail.com
License: The MIT License (MIT)
